mediagrab/__init__.py
mediagrab/__main__.py
mediagrab/content.py
mediagrab/parser.py
mediagrab-0.1.1.dist-info/LICENSE
mediagrab-0.1.1.dist-info/METADATA
mediagrab-0.1.1.dist-info/WHEEL
mediagrab-0.1.1.dist-info/entry_points.txt
mediagrab-0.1.1.dist-info/top_level.txt
mediagrab-0.1.1.dist-info/RECORD
