Metadata-Version: 2.1
Name: mediagrab
Version: 0.1.1
Summary: Python CLI for downloading videos from YouTube
Author-email: mrprikol <prikolus@proton.me>
License: MIT License
Project-URL: Repository, https://github.com/mrprikol/mediagrab
Keywords: python,cli
Classifier: Programming Language :: Python :: 3
Classifier: License :: OSI Approved :: MIT License
Classifier: Operating System :: OS Independent
Requires-Python: >=3.11
License-File: LICENSE
Requires-Dist: pytube ==15.0.0
